bankinter_converter/__init__.py
bankinter_converter/checking_account.py
bankinter_converter/cli.py
bankinter_converter/credit_card.py
bankinter_converter-0.1.0.dist-info/METADATA
bankinter_converter-0.1.0.dist-info/WHEEL
bankinter_converter-0.1.0.dist-info/entry_points.txt
bankinter_converter-0.1.0.dist-info/licenses/LICENSE
bankinter_converter-0.1.0.dist-info/RECORD
