Metadata-Version: 2.4
Name: bankinter-converter
Version: 0.1.0
Summary: A CLI tool to convert Bankinter bank statements (checking accounts and credit cards) from Excel to CSV
Project-URL: Homepage, https://github.com/barbarity/bankinter-converter
Project-URL: Repository, https://github.com/barbarity/bankinter-converter
Project-URL: Issues, https://github.com/barbarity/bankinter-converter/issues
Author-email: Joan Perez Guerrero <joanperezguerrero@gmail.com>
License: MIT
License-File: LICENSE
Keywords: banking,bankinter,converter,csv,excel,finance
Classifier: Development Status :: 4 - Beta
Classifier: Intended Audience :: Financial and Insurance Industry
Classifier: License :: OSI Approved :: MIT License
Classifier: Operating System :: OS Independent
Classifier: Programming Language :: Python :: 3
Classifier: Programming Language :: Python :: 3.8
Classifier: Programming Language :: Python :: 3.9
Classifier: Programming Language :: Python :: 3.10
Classifier: Programming Language :: Python :: 3.11
Classifier: Programming Language :: Python :: 3.12
Classifier: Programming Language :: Python :: 3.13
Classifier: Topic :: Office/Business :: Financial
Classifier: Topic :: Utilities
Requires-Python: >=3.8
Requires-Dist: openpyxl>=3.0.0
Requires-Dist: pandas>=2.0.0
Requires-Dist: xlrd>=2.0.0
Provides-Extra: dev
Requires-Dist: pytest>=7.0.0; extra == 'dev'
Requires-Dist: ruff>=0.1.0; extra == 'dev'
